bnlearn/__init__.py
bnlearn/network.py
bnlearn/learning/__init__.py
bnlearn/learning/hill_climbing.py
bnlearn/score/__init__.py
bnlearn/score/api.py
bnlearn/score/discrete.py
bnlearn/score/jax_discrete.py
bnlearn/utils/__init__.py
bnlearn/utils/graph.py
bnlearn_py-0.1.1.dist-info/METADATA
bnlearn_py-0.1.1.dist-info/WHEEL
bnlearn_py-0.1.1.dist-info/top_level.txt
bnlearn_py-0.1.1.dist-info/RECORD
