Metadata-Version: 2.4
Name: bnlearn-py
Version: 0.1.1
Summary: A Python port of the bnlearn R package for Bayesian Network structure learning
Author: Eichi Uehara
License: MIT
Requires-Python: >=3.9
Requires-Dist: numpy
Requires-Dist: pandas
Requires-Dist: scipy
Requires-Dist: jax
Requires-Dist: jaxlib
Provides-Extra: test
Requires-Dist: unittest; extra == "test"
